cfg4py/__init__.py
cfg4py/cli.py
cfg4py/config.py
cfg4py/core.py
cfg4py/resources/defaults.yaml
cfg4py/resources/production.yaml
cfg4py/resources/schema.py
cfg4py/resources/template.yaml
cfg4py/resources/test.yaml
cfg4py-0.12.1.dist-info/METADATA
cfg4py-0.12.1.dist-info/WHEEL
cfg4py-0.12.1.dist-info/entry_points.txt
cfg4py-0.12.1.dist-info/licenses/AUTHORS.md
cfg4py-0.12.1.dist-info/licenses/LICENSE
cfg4py-0.12.1.dist-info/RECORD
