Metadata-Version: 2.4
Name: cfg4py
Version: 0.12.1
Summary: Easy config (template, auto-complete), hierarchichal design, monitor config change and load on-the-fly .
License: MIT
License-File: AUTHORS.md
License-File: LICENSE
Author: Aaron Yang
Author-email: aaron_yang@jieyu.ai
Requires-Python: >=3.10,<4.0
Classifier: Development Status :: 2 - Pre-Alpha
Classifier: Intended Audience :: Developers
Classifier: License :: OSI Approved :: MIT License
Classifier: Natural Language :: English
Classifier: Programming Language :: Python :: 3
Classifier: Programming Language :: Python :: 3.10
Classifier: Programming Language :: Python :: 3.11
Classifier: Programming Language :: Python :: 3.12
Classifier: Programming Language :: Python :: 3.13
Classifier: Programming Language :: Python :: 3.14
Provides-Extra: test
Requires-Dist: APScheduler (>=3.9)
Requires-Dist: fire (>=0.5.0)
Requires-Dist: mkdocstrings-python (>=0.9.0,<0.10.0)
Requires-Dist: ruamel.yaml (>=0.17.21)
Requires-Dist: watchdog (>=2.1.9)
Project-URL: Homepage, https://github.com/zillionare/cfg4py
